{
    "table_name": "T_STG_USERS",
    "table_schema": {
        "USER_ID": "TEXT",
        "NAME": "TEXT",
        "EMAIL": "TEXT",
        "GENDER": "TEXT",
        "CITY": "TEXT",
        "SIGNUP_DATE": "TEXT",
        "CREATED_DTS": "TIMESTAMP",
        "CREATED_BY": "TEXT",
        "UPDATED_DTS": "TIMESTAMP",
        "UPDATED_BY": "TEXT",
        "UNIQUE_HASH_ID": "TEXT",
        "ROW_HASH_ID": "TEXT",
        "ACTIVE_FL": "TEXT",
        "EFFECTIVE_START_DATE": "TIMESTAMP",
        "EFFECTIVE_END_DATE": "TIMESTAMP"
    },
    "unique_keys": [
        "USER_ID"
    ],
    "transformations": [
        {
            "type": "select",
            "columns": [
                "*"
            ]
        }
    ]
}